{
  "$ref": "#/definitions/page",
  "definitions": {
    "page": {
      "type": "object",
      "properties": {
        "tinaInfo": {
          "type": "object",
          "properties": {
            "filename": {
              "type": "string"
            },
            "basename": {
              "type": "string"
            },
            "path": {
              "type": "string"
            },
            "relativePath": {
              "type": "string"
            }
          },
          "required": [
            "filename",
            "basename",
            "path",
            "relativePath"
          ],
          "additionalProperties": false
        },
        "title": {
          "type": "string"
        },
        "body": {},
        "seo": {
          "type": "object",
          "properties": {
            "title": {
              "type": "string"
            },
            "description": {
              "type": "string"
            },
            "image": {
              "type": [
                "string",
                "null"
              ]
            },
            "robots": {
              "type": "object",
              "properties": {
                "index": {
                  "type": "boolean"
                },
                "follow": {
                  "type": "boolean"
                }
              },
              "required": [
                "index",
                "follow"
              ],
              "additionalProperties": false
            }
          },
          "required": [
            "title",
            "description",
            "robots"
          ],
          "additionalProperties": false
        },
        "$schema": {
          "type": "string"
        }
      },
      "required": [
        "tinaInfo",
        "title",
        "seo"
      ],
      "additionalProperties": false
    }
  },
  "$schema": "http://json-schema.org/draft-07/schema#"
}